{
  "id": "packet:fixture:glp1-snack-demand-destruction",
  "targetCase": "glp1-snack-demand-destruction",
  "items": [
    {
      "recordId": "knowledge_reward_budget",
      "citeHandle": "K1",
      "text": "GLP-1 adoption should be read as reward-budget compression, not only a healthier-food preference shift.",
      "sourceCase": "glp1-snack-demand-destruction",
      "citation": "case-studies/glp1-snack-demand-destruction/problem-statement.md",
      "trustTier": "target-problem",
      "visibility": "public"
    },
    {
      "recordId": "knowledge_food_noise",
      "citeHandle": "K2",
      "text": "Food-noise reduction points to fewer impulse and grazing occasions across the whole household basket.",
      "sourceCase": "glp1-snack-demand-destruction",
      "citation": "case-studies/glp1-snack-demand-destruction/problem-statement.md",
      "trustTier": "target-problem",
      "visibility": "public"
    },
    {
      "recordId": "knowledge_drug_noise",
      "citeHandle": "K3",
      "text": "Early reward-system signals suggest possible knock-on demand changes in alcohol, nicotine, cannabis, shopping, and gambling.",
      "sourceCase": "glp1-snack-demand-destruction",
      "citation": "case-studies/glp1-snack-demand-destruction/problem-statement.md",
      "trustTier": "target-problem",
      "visibility": "public"
    }
  ],
  "excluded": [
    {
      "recordId": "withheld_solution_target",
      "case": "glp1-snack-demand-destruction",
      "reason": "target case solution material withheld from retrieval"
    }
  ]
}
